.bytecode 61.0
.class public synchronized com/example/SomeLombokClass
.super java/lang/Object
.inner class public static SomeLombokClassBuilder inner com/example/SomeLombokClass$SomeLombokClassBuilder outer com/example/SomeLombokClass
.inner class public static final enum Flag inner jakarta/validation/constraints/Pattern$Flag outer jakarta/validation/constraints/Pattern

.field private final 'someNullObject' Ljava/lang/Object;
.annotation visible Ljakarta/validation/constraints/Null;
.end annotation
.end field

.field private final 'someObject' Ljava/lang/Object;
.annotation visible Ljakarta/validation/constraints/NotNull;
.end annotation
.end field

.field private final 'valueWithoutAnnotation' Ljava/lang/String;

.field private final 'someNotEmptyCharSequence' Ljava/lang/CharSequence;
.annotation visible Ljakarta/validation/constraints/NotEmpty;
.end annotation
.end field

.field private final 'someNotEmptyString' Ljava/lang/String;
.annotation visible Ljakarta/validation/constraints/NotEmpty;
.end annotation
.end field

.field private final 'someNotEmptyCollection' Ljava/util/Collection;
.signature "Ljava/util/Collection<Ljava/lang/String;>;"
.annotation visible Ljakarta/validation/constraints/NotEmpty;
.end annotation
.end field

.field private final 'someNotEmptyMap' Ljava/util/Map;
.signature "Ljava/util/Map<Ljava/lang/Integer;Ljava/lang/String;>;"
.annotation visible Ljakarta/validation/constraints/NotEmpty;
.end annotation
.end field

.field private final 'someNotEmptyArray' [Ljava/lang/Integer;
.annotation visible Ljakarta/validation/constraints/NotEmpty;
.end annotation
.end field

.field private final 'someNonBlankValue' Ljava/lang/CharSequence;
.annotation visible Ljakarta/validation/constraints/NotBlank;
.end annotation
.end field

.field private final 'someNonBlankValueWithCustomMessage' Ljava/lang/String;
.annotation visible Ljakarta/validation/constraints/NotBlank;
message s = "my custom message"
.end annotation
.end field

.field private final 'stringOfLenfthBetween10And20' Ljava/lang/String;
.annotation visible Ljakarta/validation/constraints/Size;
min I = 10
max I = 20
.end annotation
.end field

.field private final 'intWith4Digits' I
.annotation visible Ljakarta/validation/constraints/Digits;
integer I = 4
fraction I = 0
.end annotation
.end field

.field private final 'someFourDigits' Ljava/lang/String;
.annotation visible Ljakarta/validation/constraints/Pattern;
regexp s = "\\d{1,4}"
flags [e Ljakarta/validation/constraints/Pattern$Flag; = "CASE_INSENSITIVE" "MULTILINE" 
.end annotation
.end field

.field private final 'anyMailAddress' Ljava/lang/String;
.annotation visible Ljakarta/validation/constraints/Email;
.end annotation
.end field

.field private final 'someTrueValue' Z
.annotation visible Ljakarta/validation/constraints/AssertTrue;
.end annotation
.end field

.field private final 'someFalseValue' Z
.annotation visible Ljakarta/validation/constraints/AssertFalse;
.end annotation
.end field

.field private final 'someTrueValueWrapper' Ljava/lang/Boolean;
.annotation visible Ljakarta/validation/constraints/AssertTrue;
.end annotation
.end field

.field private final 'someFalseValueWrapper' Ljava/lang/Boolean;
.annotation visible Ljakarta/validation/constraints/AssertFalse;
.end annotation
.end field

.field private final 'someIntPrimitiveValueThatIsMinimal42' I
.annotation visible Ljakarta/validation/constraints/Min;
value J = 42
.end annotation
.end field

.field private final 'someLongWrapperValueThatIsMinimal42' Ljava/lang/Long;
.annotation visible Ljakarta/validation/constraints/Min;
value J = 42
.end annotation
.end field

.field private final 'someLongPrimitiveValueWithDecimalMin' J
.annotation visible Ljakarta/validation/constraints/DecimalMin;
value s = "9876543210"
.end annotation
.end field

.field private final 'someBigDecimalPrimitiveValueWithDecimalMin' Ljava/math/BigDecimal;
.annotation visible Ljakarta/validation/constraints/DecimalMin;
value s = "9876543210"
.end annotation
.end field

.field private final 'someShortWrapperValueThatIsNotNullAndAbout42' Ljava/lang/Short;
.annotation visible Ljakarta/validation/constraints/NotNull;
.end annotation
.annotation visible Ljakarta/validation/constraints/Min;
value J = 41
.end annotation
.annotation visible Ljakarta/validation/constraints/Max;
value J = 43
.end annotation
.end field

.field private final 'somePastOrPresentInstant' Ljava/time/Instant;
.annotation visible Ljakarta/validation/constraints/NotNull;
.end annotation
.annotation visible Ljakarta/validation/constraints/PastOrPresent;
.end annotation
.end field

.field private static 'cache' Ljava/util/Map; signature "Ljava/util/Map<Ljava/util/AbstractMap$SimpleEntry<Ljava/lang/String;Ljava/lang/Integer;>;Ljava/util/regex/Pattern;>;"

.method private lambda$cache$0()V
return
.limit locals 1
.limit stack 0
.end method
.provide com/example/SomeLombokClass;lambda$cache$0
.desc Ljava/lang/Object;
.desc Ljava/lang/Boolean;
.desc Ljava/lang/Short;
.desc Ljava/util/Collection;
.desc [Ljava/lang/Integer;
.desc I
.desc J
.desc Ljava/util/Map;
.desc Ljava/lang/String;
.desc Ljava/time/Instant;
.desc Ljava/lang/Long;
.desc Z
.desc Ljava/math/BigDecimal;
.desc Ljava/lang/CharSequence;

.method public static main([Ljava/lang/String;)V
getstatic java/lang/System/out Ljava/io/PrintStream;
invokestatic com/example/SomeLombokClass/builder()Lcom/example/SomeLombokClass$SomeLombokClassBuilder;
ldc "isNotNull"
invokevirtual com/example/SomeLombokClass$SomeLombokClassBuilder/someObject(Ljava/lang/Object;)Lcom/example/SomeLombokClass$SomeLombokClassBuilder;
ldc ""
invokevirtual com/example/SomeLombokClass$SomeLombokClassBuilder/someNonBlankValue(Ljava/lang/CharSequence;)Lcom/example/SomeLombokClass$SomeLombokClassBuilder;
invokevirtual com/example/SomeLombokClass$SomeLombokClassBuilder/build()Lcom/example/SomeLombokClass;
invokevirtual java/io/PrintStream/println(Ljava/lang/Object;)V
return
.limit locals 1
.limit stack 3
.end method
.dep com/example/SomeLombokClass$SomeLombokClassBuilder;someNonBlankValue
.dep java/io/PrintStream;println
.dep com/example/SomeLombokClass$SomeLombokClassBuilder;someObject
.dep com/example/SomeLombokClass;builder
.dep java/lang/System;out
.dep com/example/SomeLombokClass$SomeLombokClassBuilder;build
.provide com/example/SomeLombokClass;main
.desc ()Lcom/example/SomeLombokClass$SomeLombokClassBuilder;
.desc (Ljava/lang/Object;)V
.desc (Ljava/lang/Object;)Lcom/example/SomeLombokClass$SomeLombokClassBuilder;
.desc (Ljava/lang/CharSequence;)Lcom/example/SomeLombokClass$SomeLombokClassBuilder;
.desc Ljava/io/PrintStream;
.desc ()Lcom/example/SomeLombokClass;

.method <init>(Ljava/lang/Object;Ljava/lang/Object;Ljava/lang/String;Ljava/lang/CharSequence;Ljava/lang/String;Ljava/util/Collection;Ljava/util/Map;[Ljava/lang/Integer;Ljava/lang/CharSequence;Ljava/lang/String;Ljava/lang/String;ILjava/lang/String;Ljava/lang/String;ZZLjava/lang/Boolean;Ljava/lang/Boolean;ILjava/lang/Long;JLjava/math/BigDecimal;Ljava/lang/Short;Ljava/time/Instant;)V
.signature "(Ljava/lang/Object;Ljava/lang/Object;Ljava/lang/String;Ljava/lang/CharSequence;Ljava/lang/String;Ljava/util/Collection<Ljava/lang/String;>;Ljava/util/Map<Ljava/lang/Integer;Ljava/lang/String;>;[Ljava/lang/Integer;Ljava/lang/CharSequence;Ljava/lang/String;Ljava/lang/String;ILjava/lang/String;Ljava/lang/String;ZZLjava/lang/Boolean;Ljava/lang/Boolean;ILjava/lang/Long;JLjava/math/BigDecimal;Ljava/lang/Short;Ljava/time/Instant;)V"
.annotation invisible Llombok/Generated;
.end annotation
aload 0
aload 1
aload 2
aload 3
aload 4
aload 5
aload 6
aload 7
aload 8
aload 9
aload 10
aload 11
iload 12
aload 13
aload 14
iload 15
iload 16
aload 17
aload 18
iload 19
aload 20
lload 21
aload 23
aload 24
aload 25
invokestatic com/example/SomeLombokClass/validate(Ljava/lang/Object;Ljava/lang/Object;Ljava/lang/String;Ljava/lang/CharSequence;Ljava/lang/String;Ljava/util/Collection;Ljava/util/Map;[Ljava/lang/Integer;Ljava/lang/CharSequence;Ljava/lang/String;Ljava/lang/String;ILjava/lang/String;Ljava/lang/String;ZZLjava/lang/Boolean;Ljava/lang/Boolean;ILjava/lang/Long;JLjava/math/BigDecimal;Ljava/lang/Short;Ljava/time/Instant;)V
invokespecial java/lang/Object/<init>()V
aload 0
aload 1
putfield com/example/SomeLombokClass/someNullObject Ljava/lang/Object;
aload 0
aload 2
putfield com/example/SomeLombokClass/someObject Ljava/lang/Object;
aload 0
aload 3
putfield com/example/SomeLombokClass/valueWithoutAnnotation Ljava/lang/String;
aload 0
aload 4
putfield com/example/SomeLombokClass/someNotEmptyCharSequence Ljava/lang/CharSequence;
aload 0
aload 5
putfield com/example/SomeLombokClass/someNotEmptyString Ljava/lang/String;
aload 0
aload 6
putfield com/example/SomeLombokClass/someNotEmptyCollection Ljava/util/Collection;
aload 0
aload 7
putfield com/example/SomeLombokClass/someNotEmptyMap Ljava/util/Map;
aload 0
aload 8
putfield com/example/SomeLombokClass/someNotEmptyArray [Ljava/lang/Integer;
aload 0
aload 9
putfield com/example/SomeLombokClass/someNonBlankValue Ljava/lang/CharSequence;
aload 0
aload 10
putfield com/example/SomeLombokClass/someNonBlankValueWithCustomMessage Ljava/lang/String;
aload 0
aload 11
putfield com/example/SomeLombokClass/stringOfLenfthBetween10And20 Ljava/lang/String;
aload 0
iload 12
putfield com/example/SomeLombokClass/intWith4Digits I
aload 0
aload 13
putfield com/example/SomeLombokClass/someFourDigits Ljava/lang/String;
aload 0
aload 14
putfield com/example/SomeLombokClass/anyMailAddress Ljava/lang/String;
aload 0
iload 15
putfield com/example/SomeLombokClass/someTrueValue Z
aload 0
iload 16
putfield com/example/SomeLombokClass/someFalseValue Z
aload 0
aload 17
putfield com/example/SomeLombokClass/someTrueValueWrapper Ljava/lang/Boolean;
aload 0
aload 18
putfield com/example/SomeLombokClass/someFalseValueWrapper Ljava/lang/Boolean;
aload 0
iload 19
putfield com/example/SomeLombokClass/someIntPrimitiveValueThatIsMinimal42 I
aload 0
aload 20
putfield com/example/SomeLombokClass/someLongWrapperValueThatIsMinimal42 Ljava/lang/Long;
aload 0
lload 21
putfield com/example/SomeLombokClass/someLongPrimitiveValueWithDecimalMin J
aload 0
aload 23
putfield com/example/SomeLombokClass/someBigDecimalPrimitiveValueWithDecimalMin Ljava/math/BigDecimal;
aload 0
aload 24
putfield com/example/SomeLombokClass/someShortWrapperValueThatIsNotNullAndAbout42 Ljava/lang/Short;
aload 0
aload 25
putfield com/example/SomeLombokClass/somePastOrPresentInstant Ljava/time/Instant;
return
.limit locals 26
.limit stack 26
.end method
.dep com/example/SomeLombokClass;someFalseValue
.dep com/example/SomeLombokClass;stringOfLenfthBetween10And20
.dep com/example/SomeLombokClass;anyMailAddress
.dep com/example/SomeLombokClass;someLongWrapperValueThatIsMinimal42
.dep com/example/SomeLombokClass;validate
.dep com/example/SomeLombokClass;someShortWrapperValueThatIsNotNullAndAbout42
.dep com/example/SomeLombokClass;someTrueValue
.dep com/example/SomeLombokClass;someBigDecimalPrimitiveValueWithDecimalMin
.dep com/example/SomeLombokClass;someNotEmptyCharSequence
.dep com/example/SomeLombokClass;valueWithoutAnnotation
.dep com/example/SomeLombokClass;someNotEmptyMap
.dep com/example/SomeLombokClass;someNotEmptyCollection
.dep com/example/SomeLombokClass;someFourDigits
.dep com/example/SomeLombokClass;someNullObject
.dep com/example/SomeLombokClass;someNotEmptyString
.dep com/example/SomeLombokClass;someIntPrimitiveValueThatIsMinimal42
.dep com/example/SomeLombokClass;somePastOrPresentInstant
.dep com/example/SomeLombokClass;someNotEmptyArray
.dep com/example/SomeLombokClass;someFalseValueWrapper
.dep com/example/SomeLombokClass;someTrueValueWrapper
.dep com/example/SomeLombokClass;someNonBlankValue
.dep java/lang/Object;<init>
.dep com/example/SomeLombokClass;someObject
.dep com/example/SomeLombokClass;someNonBlankValueWithCustomMessage
.dep com/example/SomeLombokClass;intWith4Digits
.dep com/example/SomeLombokClass;someLongPrimitiveValueWithDecimalMin
.provide com/example/SomeLombokClass;<init>
.desc Ljava/lang/Object;
.desc Ljava/lang/Boolean;
.desc Ljava/lang/Short;
.desc Ljava/util/Collection;
.desc [Ljava/lang/Integer;
.desc I
.desc J
.desc Ljava/util/Map;
.desc Ljava/lang/String;
.desc Ljava/time/Instant;
.desc ()V
.desc (Ljava/lang/Object;Ljava/lang/Object;Ljava/lang/String;Ljava/lang/CharSequence;Ljava/lang/String;Ljava/util/Collection;Ljava/util/Map;[Ljava/lang/Integer;Ljava/lang/CharSequence;Ljava/lang/String;Ljava/lang/String;ILjava/lang/String;Ljava/lang/String;ZZLjava/lang/Boolean;Ljava/lang/Boolean;ILjava/lang/Long;JLjava/math/BigDecimal;Ljava/lang/Short;Ljava/time/Instant;)V
.desc Ljava/lang/Long;
.desc Z
.desc Ljava/math/BigDecimal;
.desc Ljava/lang/CharSequence;

.method public static builder()Lcom/example/SomeLombokClass$SomeLombokClassBuilder;
.annotation invisible Llombok/Generated;
.end annotation
new com/example/SomeLombokClass$SomeLombokClassBuilder
dup
invokespecial com/example/SomeLombokClass$SomeLombokClassBuilder/<init>()V
areturn
.limit locals 0
.limit stack 2
.end method
.dep com/example/SomeLombokClass$SomeLombokClassBuilder;<init>
.provide com/example/SomeLombokClass;builder
.desc ()V

.method private static validate(Ljava/lang/Object;Ljava/lang/Object;Ljava/lang/String;Ljava/lang/CharSequence;Ljava/lang/String;Ljava/util/Collection;Ljava/util/Map;[Ljava/lang/Integer;Ljava/lang/CharSequence;Ljava/lang/String;Ljava/lang/String;ILjava/lang/String;Ljava/lang/String;ZZLjava/lang/Boolean;Ljava/lang/Boolean;ILjava/lang/Long;JLjava/math/BigDecimal;Ljava/lang/Short;Ljava/time/Instant;)V
.catch java/lang/IllegalArgumentException from L0 to L1 using L2
aload 0
ifnull L3
new java/lang/IllegalArgumentException
dup
ldc "someNullObject must be null"
invokespecial java/lang/IllegalArgumentException/<init>(Ljava/lang/String;)V
athrow
L3:
.stack
locals Object java/lang/Object
locals Object java/lang/Object
locals Object java/lang/String
locals Object java/lang/CharSequence
locals Object java/lang/String
locals Object java/util/Collection
locals Object java/util/Map
locals Object [Ljava/lang/Integer;
locals Object java/lang/CharSequence
locals Object java/lang/String
locals Object java/lang/String
locals Integer
locals Object java/lang/String
locals Object java/lang/String
locals Integer
locals Integer
locals Object java/lang/Boolean
locals Object java/lang/Boolean
locals Integer
locals Object java/lang/Long
locals Long
locals Object java/math/BigDecimal
locals Object java/lang/Short
locals Object java/time/Instant
.end stack
aload 1
ifnonnull L4
new java/lang/NullPointerException
dup
ldc "someObject must not be null"
invokespecial java/lang/NullPointerException/<init>(Ljava/lang/String;)V
athrow
L4:
.stack
locals Object java/lang/Object
locals Object java/lang/Object
locals Object java/lang/String
locals Object java/lang/CharSequence
locals Object java/lang/String
locals Object java/util/Collection
locals Object java/util/Map
locals Object [Ljava/lang/Integer;
locals Object java/lang/CharSequence
locals Object java/lang/String
locals Object java/lang/String
locals Integer
locals Object java/lang/String
locals Object java/lang/String
locals Integer
locals Integer
locals Object java/lang/Boolean
locals Object java/lang/Boolean
locals Integer
locals Object java/lang/Long
locals Long
locals Object java/math/BigDecimal
locals Object java/lang/Short
locals Object java/time/Instant
.end stack
aload 3
ifnonnull L5
new java/lang/NullPointerException
dup
ldc "someNotEmptyCharSequence must not be empty"
invokespecial java/lang/NullPointerException/<init>(Ljava/lang/String;)V
athrow
L5:
.stack
locals Object java/lang/Object
locals Object java/lang/Object
locals Object java/lang/String
locals Object java/lang/CharSequence
locals Object java/lang/String
locals Object java/util/Collection
locals Object java/util/Map
locals Object [Ljava/lang/Integer;
locals Object java/lang/CharSequence
locals Object java/lang/String
locals Object java/lang/String
locals Integer
locals Object java/lang/String
locals Object java/lang/String
locals Integer
locals Integer
locals Object java/lang/Boolean
locals Object java/lang/Boolean
locals Integer
locals Object java/lang/Long
locals Long
locals Object java/math/BigDecimal
locals Object java/lang/Short
locals Object java/time/Instant
.end stack
aload 3
invokeinterface java/lang/CharSequence/length()I 0
ifgt L6
new java/lang/IllegalArgumentException
dup
ldc "someNotEmptyCharSequence must not be empty"
invokespecial java/lang/IllegalArgumentException/<init>(Ljava/lang/String;)V
athrow
L6:
.stack
locals Object java/lang/Object
locals Object java/lang/Object
locals Object java/lang/String
locals Object java/lang/CharSequence
locals Object java/lang/String
locals Object java/util/Collection
locals Object java/util/Map
locals Object [Ljava/lang/Integer;
locals Object java/lang/CharSequence
locals Object java/lang/String
locals Object java/lang/String
locals Integer
locals Object java/lang/String
locals Object java/lang/String
locals Integer
locals Integer
locals Object java/lang/Boolean
locals Object java/lang/Boolean
locals Integer
locals Object java/lang/Long
locals Long
locals Object java/math/BigDecimal
locals Object java/lang/Short
locals Object java/time/Instant
.end stack
aload 4
ifnonnull L7
new java/lang/NullPointerException
dup
ldc "someNotEmptyString must not be empty"
invokespecial java/lang/NullPointerException/<init>(Ljava/lang/String;)V
athrow
L7:
.stack
locals Object java/lang/Object
locals Object java/lang/Object
locals Object java/lang/String
locals Object java/lang/CharSequence
locals Object java/lang/String
locals Object java/util/Collection
locals Object java/util/Map
locals Object [Ljava/lang/Integer;
locals Object java/lang/CharSequence
locals Object java/lang/String
locals Object java/lang/String
locals Integer
locals Object java/lang/String
locals Object java/lang/String
locals Integer
locals Integer
locals Object java/lang/Boolean
locals Object java/lang/Boolean
locals Integer
locals Object java/lang/Long
locals Long
locals Object java/math/BigDecimal
locals Object java/lang/Short
locals Object java/time/Instant
.end stack
aload 4
invokeinterface java/lang/CharSequence/length()I 0
ifgt L8
new java/lang/IllegalArgumentException
dup
ldc "someNotEmptyString must not be empty"
invokespecial java/lang/IllegalArgumentException/<init>(Ljava/lang/String;)V
athrow
L8:
.stack
locals Object java/lang/Object
locals Object java/lang/Object
locals Object java/lang/String
locals Object java/lang/CharSequence
locals Object java/lang/String
locals Object java/util/Collection
locals Object java/util/Map
locals Object [Ljava/lang/Integer;
locals Object java/lang/CharSequence
locals Object java/lang/String
locals Object java/lang/String
locals Integer
locals Object java/lang/String
locals Object java/lang/String
locals Integer
locals Integer
locals Object java/lang/Boolean
locals Object java/lang/Boolean
locals Integer
locals Object java/lang/Long
locals Long
locals Object java/math/BigDecimal
locals Object java/lang/Short
locals Object java/time/Instant
.end stack
aload 5
ifnonnull L9
new java/lang/NullPointerException
dup
ldc "someNotEmptyCollection must not be empty"
invokespecial java/lang/NullPointerException/<init>(Ljava/lang/String;)V
athrow
L9:
.stack
locals Object java/lang/Object
locals Object java/lang/Object
locals Object java/lang/String
locals Object java/lang/CharSequence
locals Object java/lang/String
locals Object java/util/Collection
locals Object java/util/Map
locals Object [Ljava/lang/Integer;
locals Object java/lang/CharSequence
locals Object java/lang/String
locals Object java/lang/String
locals Integer
locals Object java/lang/String
locals Object java/lang/String
locals Integer
locals Integer
locals Object java/lang/Boolean
locals Object java/lang/Boolean
locals Integer
locals Object java/lang/Long
locals Long
locals Object java/math/BigDecimal
locals Object java/lang/Short
locals Object java/time/Instant
.end stack
aload 5
invokeinterface java/util/Collection/size()I 0
ifgt L10
new java/lang/IllegalArgumentException
dup
ldc "someNotEmptyCollection must not be empty"
invokespecial java/lang/IllegalArgumentException/<init>(Ljava/lang/String;)V
athrow
L10:
.stack
locals Object java/lang/Object
locals Object java/lang/Object
locals Object java/lang/String
locals Object java/lang/CharSequence
locals Object java/lang/String
locals Object java/util/Collection
locals Object java/util/Map
locals Object [Ljava/lang/Integer;
locals Object java/lang/CharSequence
locals Object java/lang/String
locals Object java/lang/String
locals Integer
locals Object java/lang/String
locals Object java/lang/String
locals Integer
locals Integer
locals Object java/lang/Boolean
locals Object java/lang/Boolean
locals Integer
locals Object java/lang/Long
locals Long
locals Object java/math/BigDecimal
locals Object java/lang/Short
locals Object java/time/Instant
.end stack
aload 6
ifnonnull L11
new java/lang/NullPointerException
dup
ldc "someNotEmptyMap must not be empty"
invokespecial java/lang/NullPointerException/<init>(Ljava/lang/String;)V
athrow
L11:
.stack
locals Object java/lang/Object
locals Object java/lang/Object
locals Object java/lang/String
locals Object java/lang/CharSequence
locals Object java/lang/String
locals Object java/util/Collection
locals Object java/util/Map
locals Object [Ljava/lang/Integer;
locals Object java/lang/CharSequence
locals Object java/lang/String
locals Object java/lang/String
locals Integer
locals Object java/lang/String
locals Object java/lang/String
locals Integer
locals Integer
locals Object java/lang/Boolean
locals Object java/lang/Boolean
locals Integer
locals Object java/lang/Long
locals Long
locals Object java/math/BigDecimal
locals Object java/lang/Short
locals Object java/time/Instant
.end stack
aload 6
invokeinterface java/util/Map/size()I 0
ifgt L12
new java/lang/IllegalArgumentException
dup
ldc "someNotEmptyMap must not be empty"
invokespecial java/lang/IllegalArgumentException/<init>(Ljava/lang/String;)V
athrow
L12:
.stack
locals Object java/lang/Object
locals Object java/lang/Object
locals Object java/lang/String
locals Object java/lang/CharSequence
locals Object java/lang/String
locals Object java/util/Collection
locals Object java/util/Map
locals Object [Ljava/lang/Integer;
locals Object java/lang/CharSequence
locals Object java/lang/String
locals Object java/lang/String
locals Integer
locals Object java/lang/String
locals Object java/lang/String
locals Integer
locals Integer
locals Object java/lang/Boolean
locals Object java/lang/Boolean
locals Integer
locals Object java/lang/Long
locals Long
locals Object java/math/BigDecimal
locals Object java/lang/Short
locals Object java/time/Instant
.end stack
aload 7
ifnonnull L13
new java/lang/NullPointerException
dup
ldc "someNotEmptyArray must not be empty"
invokespecial java/lang/NullPointerException/<init>(Ljava/lang/String;)V
athrow
L13:
.stack
locals Object java/lang/Object
locals Object java/lang/Object
locals Object java/lang/String
locals Object java/lang/CharSequence
locals Object java/lang/String
locals Object java/util/Collection
locals Object java/util/Map
locals Object [Ljava/lang/Integer;
locals Object java/lang/CharSequence
locals Object java/lang/String
locals Object java/lang/String
locals Integer
locals Object java/lang/String
locals Object java/lang/String
locals Integer
locals Integer
locals Object java/lang/Boolean
locals Object java/lang/Boolean
locals Integer
locals Object java/lang/Long
locals Long
locals Object java/math/BigDecimal
locals Object java/lang/Short
locals Object java/time/Instant
.end stack
aload 7
arraylength
ifgt L14
new java/lang/IllegalArgumentException
dup
ldc "someNotEmptyArray must not be empty"
invokespecial java/lang/IllegalArgumentException/<init>(Ljava/lang/String;)V
athrow
L14:
.stack
locals Object java/lang/Object
locals Object java/lang/Object
locals Object java/lang/String
locals Object java/lang/CharSequence
locals Object java/lang/String
locals Object java/util/Collection
locals Object java/util/Map
locals Object [Ljava/lang/Integer;
locals Object java/lang/CharSequence
locals Object java/lang/String
locals Object java/lang/String
locals Integer
locals Object java/lang/String
locals Object java/lang/String
locals Integer
locals Integer
locals Object java/lang/Boolean
locals Object java/lang/Boolean
locals Integer
locals Object java/lang/Long
locals Long
locals Object java/math/BigDecimal
locals Object java/lang/Short
locals Object java/time/Instant
.end stack
aload 8
ifnonnull L15
new java/lang/NullPointerException
dup
ldc "someNonBlankValue must not be blank"
invokespecial java/lang/NullPointerException/<init>(Ljava/lang/String;)V
athrow
L15:
.stack
locals Object java/lang/Object
locals Object java/lang/Object
locals Object java/lang/String
locals Object java/lang/CharSequence
locals Object java/lang/String
locals Object java/util/Collection
locals Object java/util/Map
locals Object [Ljava/lang/Integer;
locals Object java/lang/CharSequence
locals Object java/lang/String
locals Object java/lang/String
locals Integer
locals Object java/lang/String
locals Object java/lang/String
locals Integer
locals Integer
locals Object java/lang/Boolean
locals Object java/lang/Boolean
locals Integer
locals Object java/lang/Long
locals Long
locals Object java/math/BigDecimal
locals Object java/lang/Short
locals Object java/time/Instant
.end stack
aload 8
invokeinterface java/lang/CharSequence/toString()Ljava/lang/String; 0
invokevirtual java/lang/String/trim()Ljava/lang/String;
invokevirtual java/lang/String/length()I
ifgt L16
new java/lang/IllegalArgumentException
dup
ldc "someNonBlankValue must not be blank"
invokespecial java/lang/IllegalArgumentException/<init>(Ljava/lang/String;)V
athrow
L16:
.stack
locals Object java/lang/Object
locals Object java/lang/Object
locals Object java/lang/String
locals Object java/lang/CharSequence
locals Object java/lang/String
locals Object java/util/Collection
locals Object java/util/Map
locals Object [Ljava/lang/Integer;
locals Object java/lang/CharSequence
locals Object java/lang/String
locals Object java/lang/String
locals Integer
locals Object java/lang/String
locals Object java/lang/String
locals Integer
locals Integer
locals Object java/lang/Boolean
locals Object java/lang/Boolean
locals Integer
locals Object java/lang/Long
locals Long
locals Object java/math/BigDecimal
locals Object java/lang/Short
locals Object java/time/Instant
.end stack
aload 9
ifnonnull L17
new java/lang/NullPointerException
dup
ldc "my custom message"
invokespecial java/lang/NullPointerException/<init>(Ljava/lang/String;)V
athrow
L17:
.stack
locals Object java/lang/Object
locals Object java/lang/Object
locals Object java/lang/String
locals Object java/lang/CharSequence
locals Object java/lang/String
locals Object java/util/Collection
locals Object java/util/Map
locals Object [Ljava/lang/Integer;
locals Object java/lang/CharSequence
locals Object java/lang/String
locals Object java/lang/String
locals Integer
locals Object java/lang/String
locals Object java/lang/String
locals Integer
locals Integer
locals Object java/lang/Boolean
locals Object java/lang/Boolean
locals Integer
locals Object java/lang/Long
locals Long
locals Object java/math/BigDecimal
locals Object java/lang/Short
locals Object java/time/Instant
.end stack
aload 9
invokeinterface java/lang/CharSequence/toString()Ljava/lang/String; 0
invokevirtual java/lang/String/trim()Ljava/lang/String;
invokevirtual java/lang/String/length()I
ifgt L18
new java/lang/IllegalArgumentException
dup
ldc "my custom message"
invokespecial java/lang/IllegalArgumentException/<init>(Ljava/lang/String;)V
athrow
L18:
.stack
locals Object java/lang/Object
locals Object java/lang/Object
locals Object java/lang/String
locals Object java/lang/CharSequence
locals Object java/lang/String
locals Object java/util/Collection
locals Object java/util/Map
locals Object [Ljava/lang/Integer;
locals Object java/lang/CharSequence
locals Object java/lang/String
locals Object java/lang/String
locals Integer
locals Object java/lang/String
locals Object java/lang/String
locals Integer
locals Integer
locals Object java/lang/Boolean
locals Object java/lang/Boolean
locals Integer
locals Object java/lang/Long
locals Long
locals Object java/math/BigDecimal
locals Object java/lang/Short
locals Object java/time/Instant
.end stack
iload 11
ifne L19
iconst_1
goto L20
L19:
.stack
locals Object java/lang/Object
locals Object java/lang/Object
locals Object java/lang/String
locals Object java/lang/CharSequence
locals Object java/lang/String
locals Object java/util/Collection
locals Object java/util/Map
locals Object [Ljava/lang/Integer;
locals Object java/lang/CharSequence
locals Object java/lang/String
locals Object java/lang/String
locals Integer
locals Object java/lang/String
locals Object java/lang/String
locals Integer
locals Integer
locals Object java/lang/Boolean
locals Object java/lang/Boolean
locals Integer
locals Object java/lang/Long
locals Long
locals Object java/math/BigDecimal
locals Object java/lang/Short
locals Object java/time/Instant
.end stack
iload 11
invokestatic java/lang/Math/abs(I)I
i2d
invokestatic java/lang/Math/log10(D)D
d2i
iconst_1
iadd
L20:
.stack
locals Object java/lang/Object
locals Object java/lang/Object
locals Object java/lang/String
locals Object java/lang/CharSequence
locals Object java/lang/String
locals Object java/util/Collection
locals Object java/util/Map
locals Object [Ljava/lang/Integer;
locals Object java/lang/CharSequence
locals Object java/lang/String
locals Object java/lang/String
locals Integer
locals Object java/lang/String
locals Object java/lang/String
locals Integer
locals Integer
locals Object java/lang/Boolean
locals Object java/lang/Boolean
locals Integer
locals Object java/lang/Long
locals Long
locals Object java/math/BigDecimal
locals Object java/lang/Short
locals Object java/time/Instant
stack Integer
.end stack
istore 25
iload 25
ldc 4
if_icmple L21
new java/lang/IllegalArgumentException
dup
ldc "intWith4Digits numeric value out of bounds (<4 digits>.<0 digits> expected)"
invokespecial java/lang/IllegalArgumentException/<init>(Ljava/lang/String;)V
athrow
L21:
.stack
locals Object java/lang/Object
locals Object java/lang/Object
locals Object java/lang/String
locals Object java/lang/CharSequence
locals Object java/lang/String
locals Object java/util/Collection
locals Object java/util/Map
locals Object [Ljava/lang/Integer;
locals Object java/lang/CharSequence
locals Object java/lang/String
locals Object java/lang/String
locals Integer
locals Object java/lang/String
locals Object java/lang/String
locals Integer
locals Integer
locals Object java/lang/Boolean
locals Object java/lang/Boolean
locals Integer
locals Object java/lang/Long
locals Long
locals Object java/math/BigDecimal
locals Object java/lang/Short
locals Object java/time/Instant
locals Integer
.end stack
aload 12
ifnull L22
iconst_0
istore 25
bipush 2
anewarray jakarta/validation/constraints/Pattern$Flag
dup
bipush 0
getstatic jakarta/validation/constraints/Pattern$Flag/CASE_INSENSITIVE Ljakarta/validation/constraints/Pattern$Flag;
aastore
dup
bipush 1
getstatic jakarta/validation/constraints/Pattern$Flag/MULTILINE Ljakarta/validation/constraints/Pattern$Flag;
aastore
astore 26
aload 26
arraylength
istore 27
iconst_0
istore 28
L23:
.stack
locals Object java/lang/Object
locals Object java/lang/Object
locals Object java/lang/String
locals Object java/lang/CharSequence
locals Object java/lang/String
locals Object java/util/Collection
locals Object java/util/Map
locals Object [Ljava/lang/Integer;
locals Object java/lang/CharSequence
locals Object java/lang/String
locals Object java/lang/String
locals Integer
locals Object java/lang/String
locals Object java/lang/String
locals Integer
locals Integer
locals Object java/lang/Boolean
locals Object java/lang/Boolean
locals Integer
locals Object java/lang/Long
locals Long
locals Object java/math/BigDecimal
locals Object java/lang/Short
locals Object java/time/Instant
locals Integer
locals Object [Ljakarta/validation/constraints/Pattern$Flag;
locals Integer
locals Integer
.end stack
iload 28
iload 27
if_icmpge L24
aload 26
iload 28
aaload
astore 29
iload 25
aload 29
invokevirtual jakarta/validation/constraints/Pattern$Flag/getValue()I
ior
istore 25
iinc 28 1
goto L23
L24:
.stack
locals Object java/lang/Object
locals Object java/lang/Object
locals Object java/lang/String
locals Object java/lang/CharSequence
locals Object java/lang/String
locals Object java/util/Collection
locals Object java/util/Map
locals Object [Ljava/lang/Integer;
locals Object java/lang/CharSequence
locals Object java/lang/String
locals Object java/lang/String
locals Integer
locals Object java/lang/String
locals Object java/lang/String
locals Integer
locals Integer
locals Object java/lang/Boolean
locals Object java/lang/Boolean
locals Integer
locals Object java/lang/Long
locals Long
locals Object java/math/BigDecimal
locals Object java/lang/Short
locals Object java/time/Instant
locals Integer
locals Object [Ljakarta/validation/constraints/Pattern$Flag;
locals Integer
locals Integer
.end stack
ldc "\\d{1,4}"
iload 25
invokestatic com/example/SomeLombokClass/cache(Ljava/lang/String;I)Ljava/util/regex/Pattern;
aload 12
invokevirtual java/util/regex/Pattern/matcher(Ljava/lang/CharSequence;)Ljava/util/regex/Matcher;
invokevirtual java/util/regex/Matcher/matches()Z
ifne L22
new java/lang/IllegalArgumentException
dup
ldc "someFourDigits must match \"\\d{1,4}\""
invokespecial java/lang/IllegalArgumentException/<init>(Ljava/lang/String;)V
athrow
L22:
.stack
locals Object java/lang/Object
locals Object java/lang/Object
locals Object java/lang/String
locals Object java/lang/CharSequence
locals Object java/lang/String
locals Object java/util/Collection
locals Object java/util/Map
locals Object [Ljava/lang/Integer;
locals Object java/lang/CharSequence
locals Object java/lang/String
locals Object java/lang/String
locals Integer
locals Object java/lang/String
locals Object java/lang/String
locals Integer
locals Integer
locals Object java/lang/Boolean
locals Object java/lang/Boolean
locals Integer
locals Object java/lang/Long
locals Long
locals Object java/math/BigDecimal
locals Object java/lang/Short
locals Object java/time/Instant
locals Integer
.end stack
aload 13
ifnull L25
aload 13
invokeinterface java/lang/CharSequence/length()I 0
ifeq L25
aload 13
invokeinterface java/lang/CharSequence/toString()Ljava/lang/String; 0
astore 25
aload 25
bipush 64
invokevirtual java/lang/String/lastIndexOf(I)I
istore 26
iload 26
ifge L26
new java/lang/IllegalArgumentException
dup
ldc "anyMailAddress must be a well-formed email address"
invokespecial java/lang/IllegalArgumentException/<init>(Ljava/lang/String;)V
athrow
L26:
.stack
locals Object java/lang/Object
locals Object java/lang/Object
locals Object java/lang/String
locals Object java/lang/CharSequence
locals Object java/lang/String
locals Object java/util/Collection
locals Object java/util/Map
locals Object [Ljava/lang/Integer;
locals Object java/lang/CharSequence
locals Object java/lang/String
locals Object java/lang/String
locals Integer
locals Object java/lang/String
locals Object java/lang/String
locals Integer
locals Integer
locals Object java/lang/Boolean
locals Object java/lang/Boolean
locals Integer
locals Object java/lang/Long
locals Long
locals Object java/math/BigDecimal
locals Object java/lang/Short
locals Object java/time/Instant
locals Object java/lang/String
locals Integer
.end stack
aload 25
iconst_0
iload 26
invokevirtual java/lang/String/substring(II)Ljava/lang/String;
astore 27
aload 27
invokevirtual java/lang/String/length()I
bipush 64
if_icmpgt L27
ldc "(?:[a-z0-9!#$%&'*+/=?^_`{|}~\u0080-\uffff-]+|\"(?:[a-z0-9!#$%&'*.(),<>\\[\\]:;  @+/=?^_`{|}~\u0080-\uffff-]|\\\\\\\\|\\\\\\\")+\")(?:\\.(?:[a-z0-9!#$%&'*+/=?^_`{|}~\u0080-\uffff-]+|\"(?:[a-z0-9!#$%&'*.(),<>\\[\\]:;  @+/=?^_`{|}~\u0080-\uffff-]|\\\\\\\\|\\\\\\\")+\"))*"
iconst_2
invokestatic com/example/SomeLombokClass/cache(Ljava/lang/String;I)Ljava/util/regex/Pattern;
aload 27
invokevirtual java/util/regex/Pattern/matcher(Ljava/lang/CharSequence;)Ljava/util/regex/Matcher;
invokevirtual java/util/regex/Matcher/matches()Z
ifne L28
L27:
.stack
locals Object java/lang/Object
locals Object java/lang/Object
locals Object java/lang/String
locals Object java/lang/CharSequence
locals Object java/lang/String
locals Object java/util/Collection
locals Object java/util/Map
locals Object [Ljava/lang/Integer;
locals Object java/lang/CharSequence
locals Object java/lang/String
locals Object java/lang/String
locals Integer
locals Object java/lang/String
locals Object java/lang/String
locals Integer
locals Integer
locals Object java/lang/Boolean
locals Object java/lang/Boolean
locals Integer
locals Object java/lang/Long
locals Long
locals Object java/math/BigDecimal
locals Object java/lang/Short
locals Object java/time/Instant
locals Object java/lang/String
locals Integer
locals Object java/lang/String
.end stack
new java/lang/IllegalArgumentException
dup
ldc "anyMailAddress must be a well-formed email address"
invokespecial java/lang/IllegalArgumentException/<init>(Ljava/lang/String;)V
athrow
L28:
.stack
locals Object java/lang/Object
locals Object java/lang/Object
locals Object java/lang/String
locals Object java/lang/CharSequence
locals Object java/lang/String
locals Object java/util/Collection
locals Object java/util/Map
locals Object [Ljava/lang/Integer;
locals Object java/lang/CharSequence
locals Object java/lang/String
locals Object java/lang/String
locals Integer
locals Object java/lang/String
locals Object java/lang/String
locals Integer
locals Integer
locals Object java/lang/Boolean
locals Object java/lang/Boolean
locals Integer
locals Object java/lang/Long
locals Long
locals Object java/math/BigDecimal
locals Object java/lang/Short
locals Object java/time/Instant
locals Object java/lang/String
locals Integer
locals Object java/lang/String
.end stack
aload 25
iload 26
iconst_1
iadd
invokevirtual java/lang/String/substring(I)Ljava/lang/String;
astore 28
iconst_0
istore 29
L0:
aload 28
ldc "."
invokevirtual java/lang/String/endsWith(Ljava/lang/String;)Z
ifne L29
aload 28
invokestatic java/net/IDN/toASCII(Ljava/lang/String;)Ljava/lang/String;
invokevirtual java/lang/String/length()I
sipush 255
if_icmpgt L29
ldc "(?:[a-z\u0080-\uffff0-9!#$%&'*+/=?^_`{|}~]-*)*[a-z\u0080-\uffff0-9!#$%&'*+/=?^_`{|}~]++(?:\\.(?:[a-z\u0080-\uffff0-9!#$%&'*+/=?^_`{|}~]-*)*[a-z\u0080-\uffff0-9!#$%&'*+/=?^_`{|}~]++)*|\\[[0-9]{1,3}\\.[0-9]{1,3}\\.[0-9]{1,3}\\.[0-9]{1,3}\\]|\\[IPv6:(?:(?:[0-9a-fA-F]{1,4}:){7,7}[0-9a-fA-F]{1,4}|(?:[0-9a-fA-F]{1,4}:){1,7}:|(?:[0-9a-fA-F]{1,4}:){1,6}:[0-9a-fA-F]{1,4}|(?:[0-9a-fA-F]{1,4}:){1,5}(?::[0-9a-fA-F]{1,4}){1,2}|(?:[0-9a-fA-F]{1,4}:){1,4}(?::[0-9a-fA-F]{1,4}){1,3}|(?:[0-9a-fA-F]{1,4}:){1,3}(?::[0-9a-fA-F]{1,4}){1,4}|(?:[0-9a-fA-F]{1,4}:){1,2}(?::[0-9a-fA-F]{1,4}){1,5}|[0-9a-fA-F]{1,4}:(?:(?::[0-9a-fA-F]{1,4}){1,6})|:(?:(?::[0-9a-fA-F]{1,4}){1,7}|:)|fe80:(?::[0-9a-fA-F]{0,4}){0,4}%[0-9a-zA-Z]{1,}|::(?:ffff(:0{1,4}){0,1}:){0,1}(?:(?:25[0-5]|(?:2[0-4]|1{0,1}[0-9]){0,1}[0-9])\\.){3,3}(?:25[0-5]|(?:2[0-4]|1{0,1}[0-9]){0,1}[0-9])|(?:[0-9a-fA-F]{1,4}:){1,4}:(?:(?:25[0-5]|(?:2[0-4]|1{0,1}[0-9]){0,1}[0-9])\\.){3,3}(?:25[0-5]|(?:2[0-4]|1{0,1}[0-9]){0,1}[0-9]))\\]"
iconst_2
invokestatic com/example/SomeLombokClass/cache(Ljava/lang/String;I)Ljava/util/regex/Pattern;
aload 28
invokevirtual java/util/regex/Pattern/matcher(Ljava/lang/CharSequence;)Ljava/util/regex/Matcher;
invokevirtual java/util/regex/Matcher/matches()Z
ifeq L29
iconst_1
goto L30
L29:
.stack
locals Object java/lang/Object
locals Object java/lang/Object
locals Object java/lang/String
locals Object java/lang/CharSequence
locals Object java/lang/String
locals Object java/util/Collection
locals Object java/util/Map
locals Object [Ljava/lang/Integer;
locals Object java/lang/CharSequence
locals Object java/lang/String
locals Object java/lang/String
locals Integer
locals Object java/lang/String
locals Object java/lang/String
locals Integer
locals Integer
locals Object java/lang/Boolean
locals Object java/lang/Boolean
locals Integer
locals Object java/lang/Long
locals Long
locals Object java/math/BigDecimal
locals Object java/lang/Short
locals Object java/time/Instant
locals Object java/lang/String
locals Integer
locals Object java/lang/String
locals Object java/lang/String
locals Integer
.end stack
iconst_0
L30:
.stack
locals Object java/lang/Object
locals Object java/lang/Object
locals Object java/lang/String
locals Object java/lang/CharSequence
locals Object java/lang/String
locals Object java/util/Collection
locals Object java/util/Map
locals Object [Ljava/lang/Integer;
locals Object java/lang/CharSequence
locals Object java/lang/String
locals Object java/lang/String
locals Integer
locals Object java/lang/String
locals Object java/lang/String
locals Integer
locals Integer
locals Object java/lang/Boolean
locals Object java/lang/Boolean
locals Integer
locals Object java/lang/Long
locals Long
locals Object java/math/BigDecimal
locals Object java/lang/Short
locals Object java/time/Instant
locals Object java/lang/String
locals Integer
locals Object java/lang/String
locals Object java/lang/String
locals Integer
stack Integer
.end stack
istore 29
L1:
goto L31
L2:
.stack
locals Object java/lang/Object
locals Object java/lang/Object
locals Object java/lang/String
locals Object java/lang/CharSequence
locals Object java/lang/String
locals Object java/util/Collection
locals Object java/util/Map
locals Object [Ljava/lang/Integer;
locals Object java/lang/CharSequence
locals Object java/lang/String
locals Object java/lang/String
locals Integer
locals Object java/lang/String
locals Object java/lang/String
locals Integer
locals Integer
locals Object java/lang/Boolean
locals Object java/lang/Boolean
locals Integer
locals Object java/lang/Long
locals Long
locals Object java/math/BigDecimal
locals Object java/lang/Short
locals Object java/time/Instant
locals Object java/lang/String
locals Integer
locals Object java/lang/String
locals Object java/lang/String
locals Integer
stack Object java/lang/IllegalArgumentException
.end stack
astore 30
L31:
.stack
locals Object java/lang/Object
locals Object java/lang/Object
locals Object java/lang/String
locals Object java/lang/CharSequence
locals Object java/lang/String
locals Object java/util/Collection
locals Object java/util/Map
locals Object [Ljava/lang/Integer;
locals Object java/lang/CharSequence
locals Object java/lang/String
locals Object java/lang/String
locals Integer
locals Object java/lang/String
locals Object java/lang/String
locals Integer
locals Integer
locals Object java/lang/Boolean
locals Object java/lang/Boolean
locals Integer
locals Object java/lang/Long
locals Long
locals Object java/math/BigDecimal
locals Object java/lang/Short
locals Object java/time/Instant
locals Object java/lang/String
locals Integer
locals Object java/lang/String
locals Object java/lang/String
locals Integer
.end stack
iload 29
ifne L32
new java/lang/IllegalArgumentException
dup
ldc "anyMailAddress must be a well-formed email address"
invokespecial java/lang/IllegalArgumentException/<init>(Ljava/lang/String;)V
athrow
L32:
.stack
locals Object java/lang/Object
locals Object java/lang/Object
locals Object java/lang/String
locals Object java/lang/CharSequence
locals Object java/lang/String
locals Object java/util/Collection
locals Object java/util/Map
locals Object [Ljava/lang/Integer;
locals Object java/lang/CharSequence
locals Object java/lang/String
locals Object java/lang/String
locals Integer
locals Object java/lang/String
locals Object java/lang/String
locals Integer
locals Integer
locals Object java/lang/Boolean
locals Object java/lang/Boolean
locals Integer
locals Object java/lang/Long
locals Long
locals Object java/math/BigDecimal
locals Object java/lang/Short
locals Object java/time/Instant
locals Object java/lang/String
locals Integer
locals Object java/lang/String
locals Object java/lang/String
locals Integer
.end stack
iconst_0
istore 30
bipush 0
anewarray jakarta/validation/constraints/Pattern$Flag
astore 31
aload 31
arraylength
istore 32
iconst_0
istore 33
L33:
.stack
locals Object java/lang/Object
locals Object java/lang/Object
locals Object java/lang/String
locals Object java/lang/CharSequence
locals Object java/lang/String
locals Object java/util/Collection
locals Object java/util/Map
locals Object [Ljava/lang/Integer;
locals Object java/lang/CharSequence
locals Object java/lang/String
locals Object java/lang/String
locals Integer
locals Object java/lang/String
locals Object java/lang/String
locals Integer
locals Integer
locals Object java/lang/Boolean
locals Object java/lang/Boolean
locals Integer
locals Object java/lang/Long
locals Long
locals Object java/math/BigDecimal
locals Object java/lang/Short
locals Object java/time/Instant
locals Object java/lang/String
locals Integer
locals Object java/lang/String
locals Object java/lang/String
locals Integer
locals Integer
locals Object [Ljakarta/validation/constraints/Pattern$Flag;
locals Integer
locals Integer
.end stack
iload 33
iload 32
if_icmpge L34
aload 31
iload 33
aaload
astore 34
iload 30
aload 34
invokevirtual jakarta/validation/constraints/Pattern$Flag/getValue()I
ior
istore 30
iinc 33 1
goto L33
L34:
.stack
locals Object java/lang/Object
locals Object java/lang/Object
locals Object java/lang/String
locals Object java/lang/CharSequence
locals Object java/lang/String
locals Object java/util/Collection
locals Object java/util/Map
locals Object [Ljava/lang/Integer;
locals Object java/lang/CharSequence
locals Object java/lang/String
locals Object java/lang/String
locals Integer
locals Object java/lang/String
locals Object java/lang/String
locals Integer
locals Integer
locals Object java/lang/Boolean
locals Object java/lang/Boolean
locals Integer
locals Object java/lang/Long
locals Long
locals Object java/math/BigDecimal
locals Object java/lang/Short
locals Object java/time/Instant
locals Object java/lang/String
locals Integer
locals Object java/lang/String
locals Object java/lang/String
locals Integer
locals Integer
locals Object [Ljakarta/validation/constraints/Pattern$Flag;
locals Integer
locals Integer
.end stack
ldc ".*"
iload 30
invokestatic com/example/SomeLombokClass/cache(Ljava/lang/String;I)Ljava/util/regex/Pattern;
aload 13
invokevirtual java/util/regex/Pattern/matcher(Ljava/lang/CharSequence;)Ljava/util/regex/Matcher;
invokevirtual java/util/regex/Matcher/matches()Z
ifne L25
new java/lang/IllegalArgumentException
dup
ldc "anyMailAddress must be a well-formed email address"
invokespecial java/lang/IllegalArgumentException/<init>(Ljava/lang/String;)V
athrow
L25:
.stack
locals Object java/lang/Object
locals Object java/lang/Object
locals Object java/lang/String
locals Object java/lang/CharSequence
locals Object java/lang/String
locals Object java/util/Collection
locals Object java/util/Map
locals Object [Ljava/lang/Integer;
locals Object java/lang/CharSequence
locals Object java/lang/String
locals Object java/lang/String
locals Integer
locals Object java/lang/String
locals Object java/lang/String
locals Integer
locals Integer
locals Object java/lang/Boolean
locals Object java/lang/Boolean
locals Integer
locals Object java/lang/Long
locals Long
locals Object java/math/BigDecimal
locals Object java/lang/Short
locals Object java/time/Instant
.end stack
iload 14
ifne L35
new java/lang/IllegalArgumentException
dup
ldc "someTrueValue must be true"
invokespecial java/lang/IllegalArgumentException/<init>(Ljava/lang/String;)V
athrow
L35:
.stack
locals Object java/lang/Object
locals Object java/lang/Object
locals Object java/lang/String
locals Object java/lang/CharSequence
locals Object java/lang/String
locals Object java/util/Collection
locals Object java/util/Map
locals Object [Ljava/lang/Integer;
locals Object java/lang/CharSequence
locals Object java/lang/String
locals Object java/lang/String
locals Integer
locals Object java/lang/String
locals Object java/lang/String
locals Integer
locals Integer
locals Object java/lang/Boolean
locals Object java/lang/Boolean
locals Integer
locals Object java/lang/Long
locals Long
locals Object java/math/BigDecimal
locals Object java/lang/Short
locals Object java/time/Instant
.end stack
iload 15
ifeq L36
new java/lang/IllegalArgumentException
dup
ldc "someFalseValue must be false"
invokespecial java/lang/IllegalArgumentException/<init>(Ljava/lang/String;)V
athrow
L36:
.stack
locals Object java/lang/Object
locals Object java/lang/Object
locals Object java/lang/String
locals Object java/lang/CharSequence
locals Object java/lang/String
locals Object java/util/Collection
locals Object java/util/Map
locals Object [Ljava/lang/Integer;
locals Object java/lang/CharSequence
locals Object java/lang/String
locals Object java/lang/String
locals Integer
locals Object java/lang/String
locals Object java/lang/String
locals Integer
locals Integer
locals Object java/lang/Boolean
locals Object java/lang/Boolean
locals Integer
locals Object java/lang/Long
locals Long
locals Object java/math/BigDecimal
locals Object java/lang/Short
locals Object java/time/Instant
.end stack
aload 16
ifnull L37
aload 16
invokevirtual java/lang/Boolean/booleanValue()Z
ifne L37
new java/lang/IllegalArgumentException
dup
ldc "someTrueValueWrapper must be true"
invokespecial java/lang/IllegalArgumentException/<init>(Ljava/lang/String;)V
athrow
L37:
.stack
locals Object java/lang/Object
locals Object java/lang/Object
locals Object java/lang/String
locals Object java/lang/CharSequence
locals Object java/lang/String
locals Object java/util/Collection
locals Object java/util/Map
locals Object [Ljava/lang/Integer;
locals Object java/lang/CharSequence
locals Object java/lang/String
locals Object java/lang/String
locals Integer
locals Object java/lang/String
locals Object java/lang/String
locals Integer
locals Integer
locals Object java/lang/Boolean
locals Object java/lang/Boolean
locals Integer
locals Object java/lang/Long
locals Long
locals Object java/math/BigDecimal
locals Object java/lang/Short
locals Object java/time/Instant
.end stack
aload 17
ifnull L38
aload 17
invokevirtual java/lang/Boolean/booleanValue()Z
ifeq L38
new java/lang/IllegalArgumentException
dup
ldc "someFalseValueWrapper must be false"
invokespecial java/lang/IllegalArgumentException/<init>(Ljava/lang/String;)V
athrow
L38:
.stack
locals Object java/lang/Object
locals Object java/lang/Object
locals Object java/lang/String
locals Object java/lang/CharSequence
locals Object java/lang/String
locals Object java/util/Collection
locals Object java/util/Map
locals Object [Ljava/lang/Integer;
locals Object java/lang/CharSequence
locals Object java/lang/String
locals Object java/lang/String
locals Integer
locals Object java/lang/String
locals Object java/lang/String
locals Integer
locals Integer
locals Object java/lang/Boolean
locals Object java/lang/Boolean
locals Integer
locals Object java/lang/Long
locals Long
locals Object java/math/BigDecimal
locals Object java/lang/Short
locals Object java/time/Instant
.end stack
iload 18
i2l
ldc 42
lcmp
ifge L39
new java/lang/IllegalArgumentException
dup
ldc "someIntPrimitiveValueThatIsMinimal42 must be greater than or equal to 42"
invokespecial java/lang/IllegalArgumentException/<init>(Ljava/lang/String;)V
athrow
L39:
.stack
locals Object java/lang/Object
locals Object java/lang/Object
locals Object java/lang/String
locals Object java/lang/CharSequence
locals Object java/lang/String
locals Object java/util/Collection
locals Object java/util/Map
locals Object [Ljava/lang/Integer;
locals Object java/lang/CharSequence
locals Object java/lang/String
locals Object java/lang/String
locals Integer
locals Object java/lang/String
locals Object java/lang/String
locals Integer
locals Integer
locals Object java/lang/Boolean
locals Object java/lang/Boolean
locals Integer
locals Object java/lang/Long
locals Long
locals Object java/math/BigDecimal
locals Object java/lang/Short
locals Object java/time/Instant
.end stack
aload 19
ifnull L40
aload 19
invokevirtual java/lang/Long/longValue()J
ldc 42
lcmp
ifge L40
new java/lang/IllegalArgumentException
dup
ldc "someLongWrapperValueThatIsMinimal42 must be greater than or equal to 42"
invokespecial java/lang/IllegalArgumentException/<init>(Ljava/lang/String;)V
athrow
L40:
.stack
locals Object java/lang/Object
locals Object java/lang/Object
locals Object java/lang/String
locals Object java/lang/CharSequence
locals Object java/lang/String
locals Object java/util/Collection
locals Object java/util/Map
locals Object [Ljava/lang/Integer;
locals Object java/lang/CharSequence
locals Object java/lang/String
locals Object java/lang/String
locals Integer
locals Object java/lang/String
locals Object java/lang/String
locals Integer
locals Integer
locals Object java/lang/Boolean
locals Object java/lang/Boolean
locals Integer
locals Object java/lang/Long
locals Long
locals Object java/math/BigDecimal
locals Object java/lang/Short
locals Object java/time/Instant
.end stack
new java/math/BigDecimal
dup
lload 20
invokespecial java/math/BigDecimal/<init>(J)V
new java/math/BigDecimal
dup
ldc "9876543210"
invokespecial java/math/BigDecimal/<init>(Ljava/lang/String;)V
invokevirtual java/math/BigDecimal/compareTo(Ljava/math/BigDecimal;)I
ldc 1
ifeq L41
iconst_0
goto L42
L41:
.stack
locals Object java/lang/Object
locals Object java/lang/Object
locals Object java/lang/String
locals Object java/lang/CharSequence
locals Object java/lang/String
locals Object java/util/Collection
locals Object java/util/Map
locals Object [Ljava/lang/Integer;
locals Object java/lang/CharSequence
locals Object java/lang/String
locals Object java/lang/String
locals Integer
locals Object java/lang/String
locals Object java/lang/String
locals Integer
locals Integer
locals Object java/lang/Boolean
locals Object java/lang/Boolean
locals Integer
locals Object java/lang/Long
locals Long
locals Object java/math/BigDecimal
locals Object java/lang/Short
locals Object java/time/Instant
stack Integer
.end stack
iconst_1
L42:
.stack
locals Object java/lang/Object
locals Object java/lang/Object
locals Object java/lang/String
locals Object java/lang/CharSequence
locals Object java/lang/String
locals Object java/util/Collection
locals Object java/util/Map
locals Object [Ljava/lang/Integer;
locals Object java/lang/CharSequence
locals Object java/lang/String
locals Object java/lang/String
locals Integer
locals Object java/lang/String
locals Object java/lang/String
locals Integer
locals Integer
locals Object java/lang/Boolean
locals Object java/lang/Boolean
locals Integer
locals Object java/lang/Long
locals Long
locals Object java/math/BigDecimal
locals Object java/lang/Short
locals Object java/time/Instant
stack Integer
stack Integer
.end stack
if_icmpge L43
new java/lang/IllegalArgumentException
dup
ldc "someLongPrimitiveValueWithDecimalMin must be greater than 9876543210"
invokespecial java/lang/IllegalArgumentException/<init>(Ljava/lang/String;)V
athrow
L43:
.stack
locals Object java/lang/Object
locals Object java/lang/Object
locals Object java/lang/String
locals Object java/lang/CharSequence
locals Object java/lang/String
locals Object java/util/Collection
locals Object java/util/Map
locals Object [Ljava/lang/Integer;
locals Object java/lang/CharSequence
locals Object java/lang/String
locals Object java/lang/String
locals Integer
locals Object java/lang/String
locals Object java/lang/String
locals Integer
locals Integer
locals Object java/lang/Boolean
locals Object java/lang/Boolean
locals Integer
locals Object java/lang/Long
locals Long
locals Object java/math/BigDecimal
locals Object java/lang/Short
locals Object java/time/Instant
.end stack
aload 22
ifnull L44
aload 22
new java/math/BigDecimal
dup
ldc "9876543210"
invokespecial java/math/BigDecimal/<init>(Ljava/lang/String;)V
invokevirtual java/math/BigDecimal/compareTo(Ljava/math/BigDecimal;)I
ldc 1
ifeq L45
iconst_0
goto L46
L45:
.stack
locals Object java/lang/Object
locals Object java/lang/Object
locals Object java/lang/String
locals Object java/lang/CharSequence
locals Object java/lang/String
locals Object java/util/Collection
locals Object java/util/Map
locals Object [Ljava/lang/Integer;
locals Object java/lang/CharSequence
locals Object java/lang/String
locals Object java/lang/String
locals Integer
locals Object java/lang/String
locals Object java/lang/String
locals Integer
locals Integer
locals Object java/lang/Boolean
locals Object java/lang/Boolean
locals Integer
locals Object java/lang/Long
locals Long
locals Object java/math/BigDecimal
locals Object java/lang/Short
locals Object java/time/Instant
stack Integer
.end stack
iconst_1
L46:
.stack
locals Object java/lang/Object
locals Object java/lang/Object
locals Object java/lang/String
locals Object java/lang/CharSequence
locals Object java/lang/String
locals Object java/util/Collection
locals Object java/util/Map
locals Object [Ljava/lang/Integer;
locals Object java/lang/CharSequence
locals Object java/lang/String
locals Object java/lang/String
locals Integer
locals Object java/lang/String
locals Object java/lang/String
locals Integer
locals Integer
locals Object java/lang/Boolean
locals Object java/lang/Boolean
locals Integer
locals Object java/lang/Long
locals Long
locals Object java/math/BigDecimal
locals Object java/lang/Short
locals Object java/time/Instant
stack Integer
stack Integer
.end stack
if_icmpge L44
new java/lang/IllegalArgumentException
dup
ldc "someBigDecimalPrimitiveValueWithDecimalMin must be greater than 9876543210"
invokespecial java/lang/IllegalArgumentException/<init>(Ljava/lang/String;)V
athrow
L44:
.stack
locals Object java/lang/Object
locals Object java/lang/Object
locals Object java/lang/String
locals Object java/lang/CharSequence
locals Object java/lang/String
locals Object java/util/Collection
locals Object java/util/Map
locals Object [Ljava/lang/Integer;
locals Object java/lang/CharSequence
locals Object java/lang/String
locals Object java/lang/String
locals Integer
locals Object java/lang/String
locals Object java/lang/String
locals Integer
locals Integer
locals Object java/lang/Boolean
locals Object java/lang/Boolean
locals Integer
locals Object java/lang/Long
locals Long
locals Object java/math/BigDecimal
locals Object java/lang/Short
locals Object java/time/Instant
.end stack
aload 23
ifnonnull L47
new java/lang/NullPointerException
dup
ldc "someShortWrapperValueThatIsNotNullAndAbout42 must not be null"
invokespecial java/lang/NullPointerException/<init>(Ljava/lang/String;)V
athrow
L47:
.stack
locals Object java/lang/Object
locals Object java/lang/Object
locals Object java/lang/String
locals Object java/lang/CharSequence
locals Object java/lang/String
locals Object java/util/Collection
locals Object java/util/Map
locals Object [Ljava/lang/Integer;
locals Object java/lang/CharSequence
locals Object java/lang/String
locals Object java/lang/String
locals Integer
locals Object java/lang/String
locals Object java/lang/String
locals Integer
locals Integer
locals Object java/lang/Boolean
locals Object java/lang/Boolean
locals Integer
locals Object java/lang/Long
locals Long
locals Object java/math/BigDecimal
locals Object java/lang/Short
locals Object java/time/Instant
.end stack
aload 23
ifnull L48
aload 23
invokevirtual java/lang/Short/shortValue()S
i2l
ldc 41
lcmp
ifge L48
new java/lang/IllegalArgumentException
dup
ldc "someShortWrapperValueThatIsNotNullAndAbout42 must be greater than or equal to 41"
invokespecial java/lang/IllegalArgumentException/<init>(Ljava/lang/String;)V
athrow
L48:
.stack
locals Object java/lang/Object
locals Object java/lang/Object
locals Object java/lang/String
locals Object java/lang/CharSequence
locals Object java/lang/String
locals Object java/util/Collection
locals Object java/util/Map
locals Object [Ljava/lang/Integer;
locals Object java/lang/CharSequence
locals Object java/lang/String
locals Object java/lang/String
locals Integer
locals Object java/lang/String
locals Object java/lang/String
locals Integer
locals Integer
locals Object java/lang/Boolean
locals Object java/lang/Boolean
locals Integer
locals Object java/lang/Long
locals Long
locals Object java/math/BigDecimal
locals Object java/lang/Short
locals Object java/time/Instant
.end stack
aload 23
ifnull L49
aload 23
invokevirtual java/lang/Short/shortValue()S
i2l
ldc 43
lcmp
ifle L49
new java/lang/IllegalArgumentException
dup
ldc "someShortWrapperValueThatIsNotNullAndAbout42 must be less than or equal to 43"
invokespecial java/lang/IllegalArgumentException/<init>(Ljava/lang/String;)V
athrow
L49:
.stack
locals Object java/lang/Object
locals Object java/lang/Object
locals Object java/lang/String
locals Object java/lang/CharSequence
locals Object java/lang/String
locals Object java/util/Collection
locals Object java/util/Map
locals Object [Ljava/lang/Integer;
locals Object java/lang/CharSequence
locals Object java/lang/String
locals Object java/lang/String
locals Integer
locals Object java/lang/String
locals Object java/lang/String
locals Integer
locals Integer
locals Object java/lang/Boolean
locals Object java/lang/Boolean
locals Integer
locals Object java/lang/Long
locals Long
locals Object java/math/BigDecimal
locals Object java/lang/Short
locals Object java/time/Instant
.end stack
aload 24
ifnonnull L50
new java/lang/NullPointerException
dup
ldc "somePastOrPresentInstant must not be null"
invokespecial java/lang/NullPointerException/<init>(Ljava/lang/String;)V
athrow
L50:
.stack
locals Object java/lang/Object
locals Object java/lang/Object
locals Object java/lang/String
locals Object java/lang/CharSequence
locals Object java/lang/String
locals Object java/util/Collection
locals Object java/util/Map
locals Object [Ljava/lang/Integer;
locals Object java/lang/CharSequence
locals Object java/lang/String
locals Object java/lang/String
locals Integer
locals Object java/lang/String
locals Object java/lang/String
locals Integer
locals Integer
locals Object java/lang/Boolean
locals Object java/lang/Boolean
locals Integer
locals Object java/lang/Long
locals Long
locals Object java/math/BigDecimal
locals Object java/lang/Short
locals Object java/time/Instant
.end stack
aload 24
ifnull L51
aload 24
invokestatic java/time/Instant/now()Ljava/time/Instant;
invokevirtual java/time/Instant/isAfter(Ljava/time/Instant;)Z
ifeq L51
new java/lang/IllegalArgumentException
dup
ldc "somePastOrPresentInstant must be a date in the past or in the present"
invokespecial java/lang/IllegalArgumentException/<init>(Ljava/lang/String;)V
athrow
L51:
.stack
locals Object java/lang/Object
locals Object java/lang/Object
locals Object java/lang/String
locals Object java/lang/CharSequence
locals Object java/lang/String
locals Object java/util/Collection
locals Object java/util/Map
locals Object [Ljava/lang/Integer;
locals Object java/lang/CharSequence
locals Object java/lang/String
locals Object java/lang/String
locals Integer
locals Object java/lang/String
locals Object java/lang/String
locals Integer
locals Integer
locals Object java/lang/Boolean
locals Object java/lang/Boolean
locals Integer
locals Object java/lang/Long
locals Long
locals Object java/math/BigDecimal
locals Object java/lang/Short
locals Object java/time/Instant
.end stack
return
.limit locals 35
.limit stack 4
.end method
.dep java/lang/Math;abs
.dep java/lang/CharSequence;length
.dep java/net/IDN;toASCII
.dep java/lang/Short;shortValue
.dep java/lang/String;length
.dep com/example/SomeLombokClass;cache
.dep java/lang/Long;longValue
.dep java/util/Collection;size
.dep java/lang/CharSequence;toString
.dep jakarta/validation/constraints/Pattern$Flag;CASE_INSENSITIVE
.dep java/lang/NullPointerException;<init>
.dep java/lang/String;substring
.dep java/time/Instant;isAfter
.dep jakarta/validation/constraints/Pattern$Flag;MULTILINE
.dep java/lang/String;endsWith
.dep java/lang/Boolean;booleanValue
.dep java/util/Map;size
.dep java/util/regex/Matcher;matches
.dep java/lang/String;trim
.dep java/util/regex/Pattern;matcher
.dep java/math/BigDecimal;compareTo
.dep java/lang/String;lastIndexOf
.dep jakarta/validation/constraints/Pattern$Flag;getValue
.dep java/lang/IllegalArgumentException;<init>
.dep java/math/BigDecimal;<init>
.dep java/lang/Math;log10
.dep java/time/Instant;now
.provide com/example/SomeLombokClass;validate
.desc (I)Ljava/lang/String;
.desc Ljakarta/validation/constraints/Pattern$Flag;
.desc ()Ljava/time/Instant;
.desc ()Ljava/lang/String;
.desc (D)D
.desc (Ljava/time/Instant;)Z
.desc (II)Ljava/lang/String;
.desc ()I
.desc ()J
.desc (Ljava/lang/String;)V
.desc (Ljava/lang/String;I)Ljava/util/regex/Pattern;
.desc (Ljava/lang/String;)Ljava/lang/String;
.desc (Ljava/lang/String;)Z
.desc (I)I
.desc ()S
.desc (Ljava/lang/CharSequence;)Ljava/util/regex/Matcher;
.desc ()Z
.desc (Ljava/math/BigDecimal;)I
.desc (J)V

.method private static synchronized cache(Ljava/lang/String;I)Ljava/util/regex/Pattern;
getstatic com/example/SomeLombokClass/cache Ljava/util/Map;
ifnonnull L0
new java/util/HashMap
dup
invokespecial java/util/HashMap/<init>()V
putstatic com/example/SomeLombokClass/cache Ljava/util/Map;
L0:
.stack
locals Object java/lang/String
locals Integer
.end stack
getstatic com/example/SomeLombokClass/cache Ljava/util/Map;
new java/util/AbstractMap$SimpleEntry
dup
aload 0
iload 1
invokestatic java/lang/Integer/valueOf(I)Ljava/lang/Integer;
invokespecial java/util/AbstractMap$SimpleEntry/<init>(Ljava/lang/Object;Ljava/lang/Object;)V
invokeinterface java/util/Map/computeIfAbsent(Ljava/lang/Object;Ljava/util/function/Function;)Ljava/lang/Object; 2
checkcast java/util/regex/Pattern
areturn
.limit locals 2
.limit stack 5
.end method
.dep java/lang/Integer;valueOf
.dep java/util/AbstractMap$SimpleEntry;<init>
.dep com/example/SomeLombokClass;cache
.dep java/util/Map;computeIfAbsent
.dep java/util/HashMap;<init>
.provide com/example/SomeLombokClass;cache
.desc Ljava/util/Map;
.desc (Ljava/lang/Object;Ljava/util/function/Function;)Ljava/lang/Object;
.desc ()V
.desc (Ljava/lang/Object;Ljava/lang/Object;)V
.desc (I)Ljava/lang/Integer;

.method private static synthetic lambda$cache$0$1(Ljava/util/AbstractMap$SimpleEntry;)Ljava/util/regex/Pattern;
aload 0
invokevirtual java/util/AbstractMap$SimpleEntry/getKey()Ljava/lang/Object;
checkcast java/lang/String
aload 0
invokevirtual java/util/AbstractMap$SimpleEntry/getValue()Ljava/lang/Object;
checkcast java/lang/Integer
invokevirtual java/lang/Integer/intValue()I
invokestatic java/util/regex/Pattern/compile(Ljava/lang/String;I)Ljava/util/regex/Pattern;
areturn
.limit locals 1
.limit stack 2
.end method
.dep java/util/AbstractMap$SimpleEntry;getValue
.dep java/lang/Integer;intValue
.dep java/util/regex/Pattern;compile
.dep java/util/AbstractMap$SimpleEntry;getKey
.provide com/example/SomeLombokClass;lambda$cache$0$1
.desc ()I
.desc (Ljava/lang/String;I)Ljava/util/regex/Pattern;
.desc ()Ljava/lang/Object;
