.bytecode 61.0
.class public final synchronized com/example/Mandator
.super java/lang/Object
.inner class public static final Lookup inner java/lang/invoke/MethodHandles$Lookup outer java/lang/invoke/MethodHandles

.field private static final 'RANGE_ERROR' Ljava/lang/String; = "Mandator muss zwischen 1 und 9999 liegen"

.field private static final 'NOT_NUMERIC' Ljava/lang/String; = "Mandator muss numerisch sein"

.field private final 'id' I
.annotation visible Ljakarta/validation/constraints/Min;
value J = 1
message s = "Mandator muss zwischen 1 und 9999 liegen"
.end annotation
.annotation visible Ljakarta/validation/constraints/Max;
value J = 9999
message s = "Mandator muss zwischen 1 und 9999 liegen"
.end annotation
.end field

.field private final 'cachedStringValue' Ljava/lang/String;

.field private static 'cache' Ljava/util/Map; signature "Ljava/util/Map<Ljava/util/AbstractMap$SimpleEntry<Ljava/lang/String;Ljava/lang/Integer;>;Ljava/util/regex/Pattern;>;"

.method private <init>(I)V
aload 0
iload 1
invokestatic com/example/Mandator/validate(I)V
iload 1
ldc "%1$4s"
iconst_1
anewarray java/lang/Object
dup
iconst_0
iload 1
invokestatic java/lang/Integer/valueOf(I)Ljava/lang/Integer;
aastore
invokestatic java/lang/String/format(Ljava/lang/String;[Ljava/lang/Object;)Ljava/lang/String;
bipush 32
bipush 48
invokevirtual java/lang/String/replace(CC)Ljava/lang/String;
invokespecial com/example/Mandator/<init>(ILjava/lang/String;)V
return
.limit locals 2
.limit stack 7
.end method
.dep java/lang/Integer;valueOf
.dep java/lang/String;replace
.dep java/lang/String;format
.dep com/example/Mandator;<init>
.dep com/example/Mandator;validate
.provide com/example/Mandator;<init>
.desc Ljava/lang/String;
.desc (Ljava/lang/String;[Ljava/lang/Object;)Ljava/lang/String;
.desc (CC)Ljava/lang/String;
.desc (ILjava/lang/String;)V
.desc I
.desc (I)Ljava/lang/Integer;
.desc Ljava/util/Map;
.desc (I)V

.method private <init>(ZLjava/lang/String;Z)V
aload 0
iload 1
aload 2
iload 3
invokestatic com/example/Mandator/validate(ZLjava/lang/String;Z)V
aload 2
invokestatic java/lang/Integer/parseInt(Ljava/lang/String;)I
invokespecial com/example/Mandator/<init>(I)V
return
.limit locals 4
.limit stack 4
.end method
.dep java/lang/Integer;parseInt
.dep com/example/Mandator;<init>
.dep com/example/Mandator;validate
.provide com/example/Mandator;<init>
.desc (Ljava/lang/String;)I
.desc (ZLjava/lang/String;Z)V
.desc (I)V

.method public <init>([Ljava/lang/String;)V
aload 0
aload 1
invokestatic com/example/Mandator/validate([Ljava/lang/String;)V
iconst_1
aload 1
iconst_0
aaload
iconst_0
invokespecial com/example/Mandator/<init>(ZLjava/lang/String;Z)V
return
.limit locals 2
.limit stack 4
.end method
.dep com/example/Mandator;<init>
.dep com/example/Mandator;validate
.provide com/example/Mandator;<init>
.desc (ZLjava/lang/String;Z)V
.desc ([Ljava/lang/String;)V

.method public static main([Ljava/lang/String;)V
getstatic java/lang/System/out Ljava/io/PrintStream;
new com/example/Mandator
dup
aload 0
invokespecial com/example/Mandator/<init>([Ljava/lang/String;)V
invokevirtual java/io/PrintStream/println(Ljava/lang/Object;)V
return
.limit locals 1
.limit stack 4
.end method
.dep java/io/PrintStream;println
.dep java/lang/System;out
.dep com/example/Mandator;<init>
.provide com/example/Mandator;main
.desc (Ljava/lang/Object;)V
.desc Ljava/io/PrintStream;
.desc ([Ljava/lang/String;)V

.method public toString()Ljava/lang/String;
aload 0
getfield com/example/Mandator/cachedStringValue Ljava/lang/String;
areturn
.limit locals 1
.limit stack 1
.end method
.dep com/example/Mandator;cachedStringValue
.provide com/example/Mandator;toString
.desc Ljava/lang/String;

.method public getId()I
.annotation visible Ljakarta/validation/constraints/Min;
value J = 1
message s = "Mandator muss zwischen 1 und 9999 liegen"
.end annotation
.annotation visible Ljakarta/validation/constraints/Max;
value J = 9999
message s = "Mandator muss zwischen 1 und 9999 liegen"
.end annotation
.annotation invisible Llombok/Generated;
.end annotation
aload 0
getfield com/example/Mandator/id I
ireturn
.limit locals 1
.limit stack 1
.end method
.dep com/example/Mandator;id
.provide com/example/Mandator;getId
.desc I

.method public equals(Ljava/lang/Object;)Z
.annotation invisible Llombok/Generated;
.end annotation
aload 1
aload 0
if_acmpne L0
iconst_1
ireturn
L0:
.stack
locals Object com/example/Mandator
locals Object java/lang/Object
.end stack
aload 1
instanceof com/example/Mandator
ifne L1
iconst_0
ireturn
L1:
.stack
locals Object com/example/Mandator
locals Object java/lang/Object
.end stack
aload 1
checkcast com/example/Mandator
astore 2
aload 0
invokevirtual com/example/Mandator/getId()I
aload 2
invokevirtual com/example/Mandator/getId()I
if_icmpeq L2
iconst_0
ireturn
L2:
.stack
locals Object com/example/Mandator
locals Object java/lang/Object
locals Object com/example/Mandator
.end stack
aload 0
invokevirtual com/example/Mandator/getCachedStringValue()Ljava/lang/String;
astore 3
aload 2
invokevirtual com/example/Mandator/getCachedStringValue()Ljava/lang/String;
astore 4
aload 3
ifnonnull L3
aload 4
ifnull L4
goto L5
L3:
.stack
locals Object com/example/Mandator
locals Object java/lang/Object
locals Object com/example/Mandator
locals Object java/lang/String
locals Object java/lang/String
.end stack
aload 3
aload 4
invokevirtual java/lang/Object/equals(Ljava/lang/Object;)Z
ifne L4
L5:
.stack
locals Object com/example/Mandator
locals Object java/lang/Object
locals Object com/example/Mandator
locals Object java/lang/String
locals Object java/lang/String
.end stack
iconst_0
ireturn
L4:
.stack
locals Object com/example/Mandator
locals Object java/lang/Object
locals Object com/example/Mandator
locals Object java/lang/String
locals Object java/lang/String
.end stack
iconst_1
ireturn
.limit locals 5
.limit stack 2
.end method
.dep com/example/Mandator;getId
.dep com/example/Mandator;getCachedStringValue
.dep java/lang/Object;equals
.provide com/example/Mandator;equals
.desc ()Ljava/lang/String;
.desc (Ljava/lang/Object;)Z
.desc ()I

.method public hashCode()I
.annotation invisible Llombok/Generated;
.end annotation
bipush 59
istore 1
iconst_1
istore 2
iload 2
bipush 59
imul
aload 0
invokevirtual com/example/Mandator/getId()I
iadd
istore 2
aload 0
invokevirtual com/example/Mandator/getCachedStringValue()Ljava/lang/String;
astore 3
iload 2
bipush 59
imul
aload 3
ifnonnull L0
bipush 43
goto L1
L0:
.stack
locals Object com/example/Mandator
locals Integer
locals Integer
locals Object java/lang/String
stack Integer
.end stack
aload 3
invokevirtual java/lang/Object/hashCode()I
L1:
.stack
locals Object com/example/Mandator
locals Integer
locals Integer
locals Object java/lang/String
stack Integer
stack Integer
.end stack
iadd
istore 2
iload 2
ireturn
.limit locals 4
.limit stack 2
.end method
.dep java/lang/Object;hashCode
.dep com/example/Mandator;getId
.dep com/example/Mandator;getCachedStringValue
.provide com/example/Mandator;hashCode
.desc ()Ljava/lang/String;
.desc ()I

.method private <init>(ILjava/lang/String;)V
.annotation invisible Llombok/Generated;
.end annotation
aload 0
iload 1
aload 2
invokestatic com/example/Mandator/validate(ILjava/lang/String;)V
invokespecial java/lang/Object/<init>()V
aload 0
iload 1
putfield com/example/Mandator/id I
aload 0
aload 2
putfield com/example/Mandator/cachedStringValue Ljava/lang/String;
return
.limit locals 3
.limit stack 3
.end method
.dep java/lang/Object;<init>
.dep com/example/Mandator;cachedStringValue
.dep com/example/Mandator;id
.dep com/example/Mandator;validate
.provide com/example/Mandator;<init>
.desc Ljava/lang/String;
.desc ()V
.desc (ILjava/lang/String;)V
.desc I

.method private getCachedStringValue()Ljava/lang/String;
.annotation invisible Llombok/Generated;
.end annotation
aload 0
getfield com/example/Mandator/cachedStringValue Ljava/lang/String;
areturn
.limit locals 1
.limit stack 1
.end method
.dep com/example/Mandator;cachedStringValue
.provide com/example/Mandator;getCachedStringValue
.desc Ljava/lang/String;

.method private static validate(I)V
return
.limit locals 1
.limit stack 0
.end method
.provide com/example/Mandator;validate

.method private static validate(ZLjava/lang/String;Z)V
iload 0
ifne L0
new java/lang/IllegalArgumentException
dup
ldc "foo must be true"
invokespecial java/lang/IllegalArgumentException/<init>(Ljava/lang/String;)V
athrow
L0:
.stack
locals Integer
locals Object java/lang/String
locals Integer
.end stack
aload 1
ifnonnull L1
new java/lang/NullPointerException
dup
ldc "id must not be empty"
invokespecial java/lang/NullPointerException/<init>(Ljava/lang/String;)V
athrow
L1:
.stack
locals Integer
locals Object java/lang/String
locals Integer
.end stack
aload 1
invokeinterface java/lang/CharSequence/length()I 0
ifgt L2
new java/lang/IllegalArgumentException
dup
ldc "id must not be empty"
invokespecial java/lang/IllegalArgumentException/<init>(Ljava/lang/String;)V
athrow
L2:
.stack
locals Integer
locals Object java/lang/String
locals Integer
.end stack
aload 1
ifnull L3
iconst_0
istore 3
bipush 0
anewarray jakarta/validation/constraints/Pattern$Flag
astore 4
aload 4
arraylength
istore 5
iconst_0
istore 6
L4:
.stack
locals Integer
locals Object java/lang/String
locals Integer
locals Integer
locals Object [Ljakarta/validation/constraints/Pattern$Flag;
locals Integer
locals Integer
.end stack
iload 6
iload 5
if_icmpge L5
aload 4
iload 6
aaload
astore 7
iload 3
aload 7
invokevirtual jakarta/validation/constraints/Pattern$Flag/getValue()I
ior
istore 3
iinc 6 1
goto L4
L5:
.stack
locals Integer
locals Object java/lang/String
locals Integer
locals Integer
locals Object [Ljakarta/validation/constraints/Pattern$Flag;
locals Integer
locals Integer
.end stack
ldc "\\d+"
iload 3
invokestatic com/example/Mandator/cache(Ljava/lang/String;I)Ljava/util/regex/Pattern;
aload 1
invokevirtual java/util/regex/Pattern/matcher(Ljava/lang/CharSequence;)Ljava/util/regex/Matcher;
invokevirtual java/util/regex/Matcher/matches()Z
ifne L3
new java/lang/IllegalArgumentException
dup
ldc "Mandator muss numerisch sein"
invokespecial java/lang/IllegalArgumentException/<init>(Ljava/lang/String;)V
athrow
L3:
.stack
locals Integer
locals Object java/lang/String
locals Integer
.end stack
iload 2
ifeq L6
new java/lang/IllegalArgumentException
dup
ldc "bar must be false"
invokespecial java/lang/IllegalArgumentException/<init>(Ljava/lang/String;)V
athrow
L6:
.stack
locals Integer
locals Object java/lang/String
locals Integer
.end stack
return
.limit locals 8
.limit stack 3
.end method
.dep com/example/Mandator;cache
.dep java/lang/NullPointerException;<init>
.dep java/util/regex/Matcher;matches
.dep java/lang/CharSequence;length
.dep java/util/regex/Pattern;matcher
.dep jakarta/validation/constraints/Pattern$Flag;getValue
.dep java/lang/IllegalArgumentException;<init>
.provide com/example/Mandator;validate
.desc (Ljava/lang/CharSequence;)Ljava/util/regex/Matcher;
.desc ()I
.desc ()Z
.desc (Ljava/lang/String;)V
.desc (Ljava/lang/String;I)Ljava/util/regex/Pattern;

.method private static validate([Ljava/lang/String;)V
aload 0
ifnonnull L0
new java/lang/NullPointerException
dup
ldc "args must not be empty"
invokespecial java/lang/NullPointerException/<init>(Ljava/lang/String;)V
athrow
L0:
.stack
locals Object [Ljava/lang/String;
.end stack
aload 0
arraylength
ifgt L1
new java/lang/IllegalArgumentException
dup
ldc "args must not be empty"
invokespecial java/lang/IllegalArgumentException/<init>(Ljava/lang/String;)V
athrow
L1:
.stack
locals Object [Ljava/lang/String;
.end stack
return
.limit locals 1
.limit stack 3
.end method
.dep java/lang/NullPointerException;<init>
.dep java/lang/IllegalArgumentException;<init>
.provide com/example/Mandator;validate
.desc (Ljava/lang/String;)V

.method private static validate(ILjava/lang/String;)V
iload 0
i2l
ldc 1
lcmp
ifge L0
new java/lang/IllegalArgumentException
dup
ldc "Mandator muss zwischen 1 und 9999 liegen"
invokespecial java/lang/IllegalArgumentException/<init>(Ljava/lang/String;)V
athrow
L0:
.stack
locals Integer
locals Object java/lang/String
.end stack
iload 0
i2l
ldc 9999
lcmp
ifle L1
new java/lang/IllegalArgumentException
dup
ldc "Mandator muss zwischen 1 und 9999 liegen"
invokespecial java/lang/IllegalArgumentException/<init>(Ljava/lang/String;)V
athrow
L1:
.stack
locals Integer
locals Object java/lang/String
.end stack
return
.limit locals 2
.limit stack 4
.end method
.dep java/lang/IllegalArgumentException;<init>
.provide com/example/Mandator;validate
.desc (Ljava/lang/String;)V

.method private static synchronized cache(Ljava/lang/String;I)Ljava/util/regex/Pattern;
getstatic com/example/Mandator/cache Ljava/util/Map;
ifnonnull L0
new java/util/HashMap
dup
invokespecial java/util/HashMap/<init>()V
putstatic com/example/Mandator/cache Ljava/util/Map;
L0:
.stack
locals Object java/lang/String
locals Integer
.end stack
getstatic com/example/Mandator/cache Ljava/util/Map;
new java/util/AbstractMap$SimpleEntry
dup
aload 0
iload 1
invokestatic java/lang/Integer/valueOf(I)Ljava/lang/Integer;
invokespecial java/util/AbstractMap$SimpleEntry/<init>(Ljava/lang/Object;Ljava/lang/Object;)V
invokeinterface java/util/Map/computeIfAbsent(Ljava/lang/Object;Ljava/util/function/Function;)Ljava/lang/Object; 2
checkcast java/util/regex/Pattern
areturn
.limit locals 2
.limit stack 5
.end method
.dep com/example/Mandator;cache
.dep java/lang/Integer;valueOf
.dep java/util/AbstractMap$SimpleEntry;<init>
.dep java/util/HashMap;<init>
.dep java/util/Map;computeIfAbsent
.provide com/example/Mandator;cache
.desc (Ljava/lang/Object;Ljava/util/function/Function;)Ljava/lang/Object;
.desc ()V
.desc (Ljava/lang/Object;Ljava/lang/Object;)V
.desc (I)Ljava/lang/Integer;
.desc Ljava/util/Map;

.method private static synthetic lambda$cache$0(Ljava/util/AbstractMap$SimpleEntry;)Ljava/util/regex/Pattern;
aload 0
invokevirtual java/util/AbstractMap$SimpleEntry/getKey()Ljava/lang/Object;
checkcast java/lang/String
aload 0
invokevirtual java/util/AbstractMap$SimpleEntry/getValue()Ljava/lang/Object;
checkcast java/lang/Integer
invokevirtual java/lang/Integer/intValue()I
invokestatic java/util/regex/Pattern/compile(Ljava/lang/String;I)Ljava/util/regex/Pattern;
areturn
.limit locals 1
.limit stack 2
.end method
.dep java/util/regex/Pattern;compile
.dep java/util/AbstractMap$SimpleEntry;getKey
.dep java/util/AbstractMap$SimpleEntry;getValue
.dep java/lang/Integer;intValue
.provide com/example/Mandator;lambda$cache$0
.desc ()Ljava/lang/Object;
.desc ()I
.desc (Ljava/lang/String;I)Ljava/util/regex/Pattern;
